sphinx_callouts/__init__.py
sphinx_callouts/static/css/callouts.css
sphinx_callouts-0.2.1.dist-info/licenses/LICENSE
sphinx_callouts-0.2.1.dist-info/METADATA
sphinx_callouts-0.2.1.dist-info/WHEEL
sphinx_callouts-0.2.1.dist-info/top_level.txt
sphinx_callouts-0.2.1.dist-info/RECORD
