Metadata-Version: 2.4
Name: sphinx-callouts
Version: 0.2.1
Summary: Sphinx Callouts
Author-email: Jared Dillard <jared.dillard@gmail.com>
Maintainer-email: Jared Dillard <jared.dillard@gmail.com>
License: Apache-2.0
Project-URL: download, https://pypi.org/project/sphinx-callouts/
Project-URL: source, https://github.com/jdillard/sphinx-callouts
Project-URL: changelog, https://github.com/jdillard/sphinx-callouts/blob/master/CHANGELOG.rst
Classifier: Framework :: Sphinx :: Extension
Classifier: License :: OSI Approved :: Apache Software License
Classifier: Programming Language :: Python :: 3.9
Classifier: Programming Language :: Python :: 3.10
Classifier: Programming Language :: Python :: 3.11
Classifier: Programming Language :: Python :: 3.12
Classifier: Topic :: Documentation :: Sphinx
License-File: LICENSE
Provides-Extra: dev
Requires-Dist: pytest>=7.0.0; extra == "dev"
Requires-Dist: black; extra == "dev"
Requires-Dist: flake8; extra == "dev"
Requires-Dist: mypy; extra == "dev"
Requires-Dist: isort; extra == "dev"
Requires-Dist: pre-commit; extra == "dev"
Requires-Dist: sphinx; extra == "dev"
Provides-Extra: test
Requires-Dist: pytest>=7.0.0; extra == "test"
Dynamic: license-file
